{
    "addition": {
        "26": "import com.google.common.base.Converter;\n",
        "370": "  private static final class LongConverter extends Converter<String, Long> implements Serializable {\n",
        "371": "    static final LongConverter INSTANCE = new LongConverter();\n",
        "372": "\n",
        "373": "    @Override\n",
        "374": "    protected Long doForward(String value) {\n",
        "375": "      // TODO(kevinb): remove null boilerplate (convert() will do it automatically)\n",
        "376": "      return value == null ? null : Long.decode(value);\n",
        "377": "    }\n",
        "378": "\n",
        "379": "    @Override\n",
        "380": "    protected String doBackward(Long value) {\n",
        "381": "      // TODO(kevinb): remove null boilerplate (convert() will do it automatically)\n",
        "382": "      return value == null ? null : value.toString();\n",
        "383": "    }\n",
        "384": "\n",
        "385": "    @Override\n",
        "386": "    public String toString() {\n",
        "387": "      return \"Longs.stringConverter()\";\n",
        "388": "    }\n",
        "389": "\n",
        "390": "    private Object readResolve() {\n",
        "391": "      return INSTANCE;\n",
        "392": "    }\n",
        "393": "    private static final long serialVersionUID = 1;\n",
        "394": "  }\n",
        "395": "\n",
        "396": "  /**\n",
        "397": "   * Returns a serializable converter object that converts between strings and\n",
        "398": "   * longs using {@link Long#decode} and {@link Long#toString()}.\n",
        "399": "   *\n",
        "400": "   * @since 16.0\n",
        "401": "   */\n",
        "402": "  @Beta\n",
        "403": "  public static Converter<String, Long> stringConverter() {\n",
        "404": "    return LongConverter.INSTANCE;\n",
        "405": "  }\n",
        "406": "\n"
    },
    "removed": {}
}