{
    "addition": {
        "1": "/*\n",
        "2": " * Copyright (C) 2013 The Guava Authors\n",
        "3": " *\n",
        "4": " * Licensed under the Apache License, Version 2.0 (the \"License\");\n",
        "5": " * you may not use this file except in compliance with the License.\n",
        "6": " * You may obtain a copy of the License at\n",
        "7": " *\n",
        "8": " * http://www.apache.org/licenses/LICENSE-2.0\n",
        "9": " *\n",
        "10": " * Unless required by applicable law or agreed to in writing, software\n",
        "11": " * distributed under the License is distributed on an \"AS IS\" BASIS,\n",
        "12": " * WITHOUT WARRANTIES OR CONDITIONS OF ANY KIND, either express or implied.\n",
        "13": " * See the License for the specific language governing permissions and\n",
        "14": " * limitations under the License.\n",
        "15": " */\n",
        "16": "\n",
        "17": "package com.google.common.collect.testing.testers;\n",
        "18": "\n",
        "19": "import static com.google.common.collect.testing.features.CollectionFeature.KNOWN_ORDER;\n",
        "20": "\n",
        "21": "import com.google.common.annotations.GwtCompatible;\n",
        "22": "import com.google.common.collect.testing.AbstractCollectionTester;\n",
        "23": "import com.google.common.collect.testing.Helpers;\n",
        "24": "import com.google.common.collect.testing.features.CollectionFeature;\n",
        "25": "import java.util.Arrays;\n",
        "26": "\n",
        "27": "/**\n",
        "28": " * A generic JUnit test which tests {@code stream} operations on a collection.\n",
        "29": " * Can't be invoked directly; please see\n",
        "30": " * {@link com.google.common.collect.testing.CollectionTestSuiteBuilder}.\n",
        "31": " *\n",
        "32": " * @author Louis Wasserman\n",
        "33": " */\n",
        "34": "@GwtCompatible\n",
        "35": "public class CollectionStreamTester<E> extends AbstractCollectionTester<E> {\n",
        "36": "  /*\n",
        "37": "   * We're not really testing the implementation of Stream, only that we're getting a Stream\n",
        "38": "   * that corresponds to the expected elements.\n",
        "39": "   */\n",
        "40": "\n",
        "41": "  @CollectionFeature.Require(absent = KNOWN_ORDER)\n",
        "42": "  public void testStreamToArrayUnknownOrder() {\n",
        "43": "    synchronized (collection) { // to allow Collections.synchronized* tests to pass\n",
        "44": "      Helpers.assertEqualIgnoringOrder(\n",
        "45": "          getSampleElements(), Arrays.asList(collection.stream().toArray()));\n",
        "46": "    }\n",
        "47": "  }\n",
        "48": "\n",
        "49": "  @CollectionFeature.Require(KNOWN_ORDER)\n",
        "50": "  public void testStreamToArrayKnownOrder() {\n",
        "51": "    synchronized (collection) { // to allow Collections.synchronized* tests to pass\n",
        "52": "      assertEquals(getOrderedElements(), Arrays.asList(collection.stream().toArray()));\n",
        "53": "    }\n",
        "54": "  }\n",
        "55": "\n",
        "56": "  public void testStreamCount() {\n",
        "57": "    synchronized (collection) { // to allow Collections.synchronized* tests to pass\n",
        "58": "      assertEquals(getNumElements(), collection.stream().count());\n",
        "59": "    }\n",
        "60": "  }\n",
        "61": "}\n"
    },
    "removed": {}
}